{ 
  "id":"acct_1FOQvcFJUfoQsGN8",
  "object":"account",
  "business_profile":{ 
    "mcc":null,
    "name":"My new business",
    "product_description":null,
    "support_address":null,
    "support_email":null,
    "support_phone":null,
    "support_url":null,
    "url":null
  },
  "business_type":"company",
  "capabilities":{ 
    "card_payments":"active",
    "transfers":"inactive"
  },
  "charges_enabled":false,
  "company":{ 
    "address":{ 
      "city":"Brighton",
      "country":"GB",
      "line1":"21 Palmeira Street",
      "line2":"Flat 10",
      "postal_code":"BN1 4QR",
      "state":"East Sussex"
    },
    "directors_provided":true,
    "name":"My new business",
    "owners_provided":true,
    "tax_id_provided":false,
    "verification":{ 
      "document":{ 
        "back":null,
        "details":null,
        "details_code":null,
        "front":null
      }
    }
  },
  "country":"GB",
  "created":1569857808,
  "default_currency":"gbp",
  "details_submitted":false,
  "email":null,
  "external_accounts":{ 
    "object":"list",
    "data":[ 

    ],
    "has_more":false,
    "total_count":0,
    "url":"/v1/accounts/acct_1FOQvcFJUfoQsGN8/external_accounts"
  },
  "metadata":{ 

  },
  "payouts_enabled":false,
  "requirements":{ 
    "current_deadline":null,
    "currently_due":[ 
      "business_profile.mcc",
      "business_profile.url",
      "company.phone",
      "company.tax_id",
      "external_account",
      "person_FuFQmjg5UVOdIU.relationship.title",
      "person_FuFRIanLwTyQt0.relationship.title",
      "person_FuFkzT10m6RVIE.relationship.title",
      "person_FuFqPnlD9ZIaXm.relationship.title",
      "person_FuFudVAodgkpLs.relationship.title",
      "relationship.account_opener"
    ],
    "disabled_reason":"requirements.past_due",
    "eventually_due":[ 
      "business_profile.mcc",
      "business_profile.url",
      "company.phone",
      "company.tax_id",
      "external_account",
      "person_FuFQmjg5UVOdIU.relationship.title",
      "person_FuFRIanLwTyQt0.relationship.title",
      "person_FuFkzT10m6RVIE.relationship.title",
      "person_FuFqPnlD9ZIaXm.relationship.title",
      "person_FuFudVAodgkpLs.relationship.title",
      "relationship.account_opener"
    ],
    "past_due":[ 
      "business_profile.mcc",
      "business_profile.url",
      "company.phone",
      "company.tax_id",
      "external_account",
      "person_FuFQmjg5UVOdIU.relationship.title",
      "person_FuFRIanLwTyQt0.relationship.title",
      "person_FuFkzT10m6RVIE.relationship.title",
      "person_FuFqPnlD9ZIaXm.relationship.title",
      "person_FuFudVAodgkpLs.relationship.title",
      "relationship.account_opener"
    ],
    "pending_verification":[ 

    ]
  },
  "settings":{ 
    "branding":{ 
      "icon":null,
      "logo":null,
      "primary_color":null
    },
    "card_payments":{ 
      "decline_on":{ 
        "avs_failure":false,
        "cvc_failure":false
      },
      "statement_descriptor_prefix":null
    },
    "dashboard":{ 
      "display_name":null,
      "timezone":"Etc/UTC"
    },
    "payments":{ 
      "statement_descriptor":"",
      "statement_descriptor_kana":null,
      "statement_descriptor_kanji":null
    },
    "payouts":{ 
      "debit_negative_balances":false,
      "schedule":{ 
        "delay_days":7,
        "interval":"daily"
      },
      "statement_descriptor":null
    }
  },
  "tos_acceptance":{ 
    "date":1569857807,
    "ip":"86.13.178.22",
    "user_agent":"Mozilla/5.0 (Macintosh; Intel Mac OS X 10_14_3) AppleWebKit/537.36 (KHTML, like Gecko) Chrome/77.0.3865.90 Safari/537.36"
  },
  "type":"custom"
}